{
  "fabric:load_conditions": [
    {
      "condition": "fabric:any_mod_loaded",
      "values": ["nbtcrafting"]
    },
    {
      "condition": "kiwi:is_loaded",
      "module": "passablefoliage:enchantment"
    }
  ],
  "type": "nbtcrafting:wrapped",
  "recipe": {
    "type": "crafting_shapeless",
    "ingredients": [
      {
        "item": "enchanted_book"
      },
      {
        "tag": "leaves"
      }
    ],
    "result": {
      "item": "enchanted_book",
      "data": {
        "StoredEnchantments": [
          {
            "lvl": 1,
            "id": "passablefoliage:leaf_walker"
          }
        ]
      }
    }
  }
}
